Metadata-Version: 1.1
Name: read-gen
Version: 0.1.3
Summary: Produce error-prone reads from a generated sequence
Home-page: http://bitbucket.org/bilalakil/readgen
Author: Bilal Akil
Author-email: mail@bilalakil.me
License: MIT
Platform: any
Classifier: Intended Audience :: Science/Research
Classifier: Topic :: Scientific/Engineering :: Bio-Informatics
Classifier: License :: OSI Approved :: MIT License
Classifier: Natural Language :: English
Classifier: Operating System :: OS Independent
Classifier: Programming Language :: Python
